{"data":{"markdownRemark":null,"npmPackage":{"name":"gatsby-mdx","description":"mdx integration for gatsby","keywords":["gatsby","gatsby-plugin","gatsby-transformer-plugin","mdx","markdown","remark","rehype"],"lastPublisher":{"name":"biscarch","avatar":"https://gravatar.com/avatar/5f7798f819ff4add0e78e599ae83b01f"},"repository":null,"readme":{"childMarkdownRemark":{"html":"<p><img src=\"../../img/gatsby-mdx.png\" alt=\"Logo\"></p>\n<blockquote>\n<p>gatsby-mdx is <em>the</em> official integration for using <a href=\"https://mdxjs.com\">MDX</a>\nwith <a href=\"https://www.gatsbyjs.org/\">Gatsby</a>.</p>\n</blockquote>\n<h1 id=\"whats-mdx\"><a href=\"#whats-mdx\" aria-label=\"whats mdx permalink\" class=\"anchor\"><svg aria-hidden=\"true\" focusable=\"false\" height=\"16\" version=\"1.1\" viewBox=\"0 0 16 16\" width=\"16\"><path fill-rule=\"evenodd\" d=\"M4 9h1v1H4c-1.5 0-3-1.69-3-3.5S2.55 3 4 3h4c1.45 0 3 1.69 3 3.5 0 1.41-.91 2.72-2 3.25V8.59c.58-.45 1-1.27 1-2.09C10 5.22 8.98 4 8 4H4c-.98 0-2 1.22-2 2.5S3 9 4 9zm9-3h-1v1h1c1 0 2 1.22 2 2.5S13.98 12 13 12H9c-.98 0-2-1.22-2-2.5 0-.83.42-1.64 1-2.09V6.25c-1.09.53-2 1.84-2 3.25C6 11.31 7.55 13 9 13h4c1.45 0 3-1.69 3-3.5S14.5 6 13 6z\"></path></svg></a>What’s MDX?</h1>\n<p>MDX is markdown for the component era. It lets you write JSX embedded inside\nmarkdown. It’s a great combination because it allows you to use markdown’s often\nterse syntax (such as <code class=\"language-text\"># heading</code>) for the little things and JSX for more advanced\ncomponents.</p>\n<h3 id=\"read-more-about-mdx\"><a href=\"#read-more-about-mdx\" aria-label=\"read more about mdx permalink\" class=\"anchor\"><svg aria-hidden=\"true\" focusable=\"false\" height=\"16\" version=\"1.1\" viewBox=\"0 0 16 16\" width=\"16\"><path fill-rule=\"evenodd\" d=\"M4 9h1v1H4c-1.5 0-3-1.69-3-3.5S2.55 3 4 3h4c1.45 0 3 1.69 3 3.5 0 1.41-.91 2.72-2 3.25V8.59c.58-.45 1-1.27 1-2.09C10 5.22 8.98 4 8 4H4c-.98 0-2 1.22-2 2.5S3 9 4 9zm9-3h-1v1h1c1 0 2 1.22 2 2.5S13.98 12 13 12H9c-.98 0-2-1.22-2-2.5 0-.83.42-1.64 1-2.09V6.25c-1.09.53-2 1.84-2 3.25C6 11.31 7.55 13 9 13h4c1.45 0 3-1.69 3-3.5S14.5 6 13 6z\"></path></svg></a>Read more about MDX</h3>\n<ul>\n<li><a href=\"https://www.gatsbyjs.org/docs/mdx/why/\">:grey_question: Why MDX?</a></li>\n<li><a href=\"https://www.gatsbyjs.org/docs/mdx/\">:books: Gatsby guide</a></li>\n<li><a href=\"https://mdxjs.com\">:mega: Language</a></li>\n<li><a href=\"https://github.com/mdx-js/specification\">:woman_scientist: Specification</a></li>\n</ul>\n<h2 id=\"table-of-contents\"><a href=\"#table-of-contents\" aria-label=\"table of contents permalink\" class=\"anchor\"><svg aria-hidden=\"true\" focusable=\"false\" height=\"16\" version=\"1.1\" viewBox=\"0 0 16 16\" width=\"16\"><path fill-rule=\"evenodd\" d=\"M4 9h1v1H4c-1.5 0-3-1.69-3-3.5S2.55 3 4 3h4c1.45 0 3 1.69 3 3.5 0 1.41-.91 2.72-2 3.25V8.59c.58-.45 1-1.27 1-2.09C10 5.22 8.98 4 8 4H4c-.98 0-2 1.22-2 2.5S3 9 4 9zm9-3h-1v1h1c1 0 2 1.22 2 2.5S13.98 12 13 12H9c-.98 0-2-1.22-2-2.5 0-.83.42-1.64 1-2.09V6.25c-1.09.53-2 1.84-2 3.25C6 11.31 7.55 13 9 13h4c1.45 0 3-1.69 3-3.5S14.5 6 13 6z\"></path></svg></a>Table of contents</h2>\n<ul>\n<li><a href=\"#installation\">Installation</a></li>\n<li>\n<p><a href=\"#usage\">Usage</a></p>\n<ul>\n<li><a href=\"#configuration\">Configuration</a></li>\n<li><a href=\"#extensions\">Extensions</a></li>\n<li><a href=\"#default-layouts\">Default layouts</a></li>\n<li><a href=\"#global-scope\">Global scope</a></li>\n<li><a href=\"#gatsby-remark-plugins\">Gatbsy remark plugins</a></li>\n<li><a href=\"#md-plugins\">Markdown plugins</a></li>\n<li><a href=\"#hast-plugins\">HAST plugins</a></li>\n<li><a href=\"#media-types\">Media types</a></li>\n<li><a href=\"#components\">Components</a></li>\n<li><a href=\"#mdxprovider\">MDXProvider</a></li>\n<li><a href=\"#mdxrenderer\">MDXRenderer</a></li>\n</ul>\n</li>\n</ul>\n<h2 id=\"installation\"><a href=\"#installation\" aria-label=\"installation permalink\" class=\"anchor\"><svg aria-hidden=\"true\" focusable=\"false\" height=\"16\" version=\"1.1\" viewBox=\"0 0 16 16\" width=\"16\"><path fill-rule=\"evenodd\" d=\"M4 9h1v1H4c-1.5 0-3-1.69-3-3.5S2.55 3 4 3h4c1.45 0 3 1.69 3 3.5 0 1.41-.91 2.72-2 3.25V8.59c.58-.45 1-1.27 1-2.09C10 5.22 8.98 4 8 4H4c-.98 0-2 1.22-2 2.5S3 9 4 9zm9-3h-1v1h1c1 0 2 1.22 2 2.5S13.98 12 13 12H9c-.98 0-2-1.22-2-2.5 0-.83.42-1.64 1-2.09V6.25c-1.09.53-2 1.84-2 3.25C6 11.31 7.55 13 9 13h4c1.45 0 3-1.69 3-3.5S14.5 6 13 6z\"></path></svg></a>Installation</h2>\n<p>Install with npm:</p>\n<div class=\"gatsby-highlight\" data-language=\"sh\"><pre class=\"language-sh\"><code class=\"language-sh\">npm install --save gatsby-mdx @mdx-js/mdx @mdx-js/tag</code></pre></div>\n<p>Install with yarn:</p>\n<div class=\"gatsby-highlight\" data-language=\"sh\"><pre class=\"language-sh\"><code class=\"language-sh\">yarn add gatsby-mdx @mdx-js/mdx @mdx-js/tag</code></pre></div>\n<h2 id=\"usage\"><a href=\"#usage\" aria-label=\"usage permalink\" class=\"anchor\"><svg aria-hidden=\"true\" focusable=\"false\" height=\"16\" version=\"1.1\" viewBox=\"0 0 16 16\" width=\"16\"><path fill-rule=\"evenodd\" d=\"M4 9h1v1H4c-1.5 0-3-1.69-3-3.5S2.55 3 4 3h4c1.45 0 3 1.69 3 3.5 0 1.41-.91 2.72-2 3.25V8.59c.58-.45 1-1.27 1-2.09C10 5.22 8.98 4 8 4H4c-.98 0-2 1.22-2 2.5S3 9 4 9zm9-3h-1v1h1c1 0 2 1.22 2 2.5S13.98 12 13 12H9c-.98 0-2-1.22-2-2.5 0-.83.42-1.64 1-2.09V6.25c-1.09.53-2 1.84-2 3.25C6 11.31 7.55 13 9 13h4c1.45 0 3-1.69 3-3.5S14.5 6 13 6z\"></path></svg></a>Usage</h2>\n<p>After installing gatsby-mdx you can add it to your plugins list in your\n<code class=\"language-text\">gatsby-config.js</code>.</p>\n<div class=\"gatsby-highlight\" data-language=\"js\"><pre class=\"language-js\"><code class=\"language-js\">module<span class=\"token punctuation\">.</span>exports <span class=\"token operator\">=</span> <span class=\"token punctuation\">{</span>\n  plugins<span class=\"token punctuation\">:</span> <span class=\"token punctuation\">[</span><span class=\"token template-string\"><span class=\"token string\">`gatsby-mdx`</span></span><span class=\"token punctuation\">]</span>\n<span class=\"token punctuation\">}</span><span class=\"token punctuation\">;</span></code></pre></div>\n<p>By default, this configuration will allow you to create pages\nwith <code class=\"language-text\">.mdx</code> files in <code class=\"language-text\">src/pages</code> and will process any Gatsby nodes\nwith Markdown media types into MDX content.</p>\n<h3 id=\"configuration\"><a href=\"#configuration\" aria-label=\"configuration permalink\" class=\"anchor\"><svg aria-hidden=\"true\" focusable=\"false\" height=\"16\" version=\"1.1\" viewBox=\"0 0 16 16\" width=\"16\"><path fill-rule=\"evenodd\" d=\"M4 9h1v1H4c-1.5 0-3-1.69-3-3.5S2.55 3 4 3h4c1.45 0 3 1.69 3 3.5 0 1.41-.91 2.72-2 3.25V8.59c.58-.45 1-1.27 1-2.09C10 5.22 8.98 4 8 4H4c-.98 0-2 1.22-2 2.5S3 9 4 9zm9-3h-1v1h1c1 0 2 1.22 2 2.5S13.98 12 13 12H9c-.98 0-2-1.22-2-2.5 0-.83.42-1.64 1-2.09V6.25c-1.09.53-2 1.84-2 3.25C6 11.31 7.55 13 9 13h4c1.45 0 3-1.69 3-3.5S14.5 6 13 6z\"></path></svg></a>Configuration</h3>\n<p>gatsby-mdx exposes a configuration API that can be used similarly to\nany other Gatsby plugin. You can define MDX extensions, layouts, global\nscope, and more.</p>\n<table>\n<thead>\n<tr>\n<th>Key</th>\n<th>Default</th>\n<th>Description</th>\n</tr>\n</thead>\n<tbody>\n<tr>\n<td><a href=\"#extensions\"><code class=\"language-text\">extensions</code></a></td>\n<td><code class=\"language-text\">[&quot;.mdx&quot;]</code></td>\n<td>Configure the file extensions that gatsby-mdx will process</td>\n</tr>\n<tr>\n<td><a href=\"#default-layouts\"><code class=\"language-text\">defaultLayouts</code></a></td>\n<td><code class=\"language-text\">{}</code></td>\n<td>Set the layout components for MDX source types</td>\n</tr>\n<tr>\n<td><a href=\"#global-scope\"><code class=\"language-text\">globalScope</code></a></td>\n<td><code class=\"language-text\">&quot;&quot;</code></td>\n<td>Define components and variables that are accessible to all MDX files</td>\n</tr>\n<tr>\n<td><a href=\"#gatsby-remark-plugins\">`gatsbyRemarkPlugins</a> | <code class=\"language-text\">[]</code> | Use Gatsby-specific remark plugins</td>\n<td></td>\n<td></td>\n</tr>\n<tr>\n<td><a href=\"#md-plugins\"><code class=\"language-text\">mdPlugins</code></a></td>\n<td><code class=\"language-text\">[]</code></td>\n<td>Specify remark plugins</td>\n</tr>\n<tr>\n<td><a href=\"#hast-plugins\"><code class=\"language-text\">hastPlugins</code></a></td>\n<td><code class=\"language-text\">[]</code></td>\n<td>Specify rehype plugins</td>\n</tr>\n<tr>\n<td><a href=\"#media-types\"><code class=\"language-text\">mediaTypes</code></a></td>\n<td><code class=\"language-text\">[&quot;text/markdown&quot;, &quot;text/x-markdown&quot;]</code></td>\n<td>Determine which media types are processed by MDX</td>\n</tr>\n</tbody>\n</table>\n<h4 id=\"extensions\"><a href=\"#extensions\" aria-label=\"extensions permalink\" class=\"anchor\"><svg aria-hidden=\"true\" focusable=\"false\" height=\"16\" version=\"1.1\" viewBox=\"0 0 16 16\" width=\"16\"><path fill-rule=\"evenodd\" d=\"M4 9h1v1H4c-1.5 0-3-1.69-3-3.5S2.55 3 4 3h4c1.45 0 3 1.69 3 3.5 0 1.41-.91 2.72-2 3.25V8.59c.58-.45 1-1.27 1-2.09C10 5.22 8.98 4 8 4H4c-.98 0-2 1.22-2 2.5S3 9 4 9zm9-3h-1v1h1c1 0 2 1.22 2 2.5S13.98 12 13 12H9c-.98 0-2-1.22-2-2.5 0-.83.42-1.64 1-2.09V6.25c-1.09.53-2 1.84-2 3.25C6 11.31 7.55 13 9 13h4c1.45 0 3-1.69 3-3.5S14.5 6 13 6z\"></path></svg></a>Extensions</h4>\n<p>By default, only files with the <code class=\"language-text\">.mdx</code> file extension are treated as MDX when\nusing <code class=\"language-text\">gatsby-source-filesystem</code>. To use <code class=\"language-text\">.md</code> or other file extensions, you can\ndefine an array of file extensions in the <code class=\"language-text\">gatsby-mdx</code> section of your\n<code class=\"language-text\">gatsby-config.js</code>.</p>\n<div class=\"gatsby-highlight\" data-language=\"js\"><pre class=\"language-js\"><code class=\"language-js\"><span class=\"token comment\">// gatsby-config.js</span>\nmodule<span class=\"token punctuation\">.</span>exports <span class=\"token operator\">=</span> <span class=\"token punctuation\">{</span>\n  plugins<span class=\"token punctuation\">:</span> <span class=\"token punctuation\">[</span>\n    <span class=\"token punctuation\">{</span>\n      resolve<span class=\"token punctuation\">:</span> <span class=\"token template-string\"><span class=\"token string\">`gatsby-mdx`</span></span><span class=\"token punctuation\">,</span>\n      options<span class=\"token punctuation\">:</span> <span class=\"token punctuation\">{</span>\n        extensions<span class=\"token punctuation\">:</span> <span class=\"token punctuation\">[</span><span class=\"token template-string\"><span class=\"token string\">`.mdx`</span></span><span class=\"token punctuation\">,</span> <span class=\"token template-string\"><span class=\"token string\">`.md`</span></span><span class=\"token punctuation\">]</span>\n      <span class=\"token punctuation\">}</span>\n    <span class=\"token punctuation\">}</span>\n  <span class=\"token punctuation\">]</span>\n<span class=\"token punctuation\">}</span><span class=\"token punctuation\">;</span></code></pre></div>\n<h4 id=\"default-layouts\"><a href=\"#default-layouts\" aria-label=\"default layouts permalink\" class=\"anchor\"><svg aria-hidden=\"true\" focusable=\"false\" height=\"16\" version=\"1.1\" viewBox=\"0 0 16 16\" width=\"16\"><path fill-rule=\"evenodd\" d=\"M4 9h1v1H4c-1.5 0-3-1.69-3-3.5S2.55 3 4 3h4c1.45 0 3 1.69 3 3.5 0 1.41-.91 2.72-2 3.25V8.59c.58-.45 1-1.27 1-2.09C10 5.22 8.98 4 8 4H4c-.98 0-2 1.22-2 2.5S3 9 4 9zm9-3h-1v1h1c1 0 2 1.22 2 2.5S13.98 12 13 12H9c-.98 0-2-1.22-2-2.5 0-.83.42-1.64 1-2.09V6.25c-1.09.53-2 1.84-2 3.25C6 11.31 7.55 13 9 13h4c1.45 0 3-1.69 3-3.5S14.5 6 13 6z\"></path></svg></a>Default layouts</h4>\n<p><code class=\"language-text\">defaultLayouts</code> takes an object where the <code class=\"language-text\">key</code> is the <code class=\"language-text\">name</code> key of\nthe <code class=\"language-text\">gatsby-source-filesystem</code> configuration you want to\ntarget. <code class=\"language-text\">default</code> applies to any MDX file that doesn’t already have a\nlayout defined, even if it’s imported manually using <code class=\"language-text\">import MDX from &#39;./thing.mdx</code>.</p>\n<div class=\"gatsby-highlight\" data-language=\"js\"><pre class=\"language-js\"><code class=\"language-js\"><span class=\"token comment\">// gatsby-config.js</span>\nmodule<span class=\"token punctuation\">.</span>exports <span class=\"token operator\">=</span> <span class=\"token punctuation\">{</span>\n  plugins<span class=\"token punctuation\">:</span> <span class=\"token punctuation\">[</span>\n    <span class=\"token punctuation\">{</span>\n      resolve<span class=\"token punctuation\">:</span> <span class=\"token template-string\"><span class=\"token string\">`gatsby-mdx`</span></span><span class=\"token punctuation\">,</span>\n      options<span class=\"token punctuation\">:</span> <span class=\"token punctuation\">{</span>\n        defaultLayouts<span class=\"token punctuation\">:</span> <span class=\"token punctuation\">{</span>\n          posts<span class=\"token punctuation\">:</span> require<span class=\"token punctuation\">.</span><span class=\"token function\">resolve</span><span class=\"token punctuation\">(</span><span class=\"token string\">\"./src/components/posts-layout.js\"</span><span class=\"token punctuation\">)</span><span class=\"token punctuation\">,</span>\n          <span class=\"token keyword\">default</span><span class=\"token punctuation\">:</span> require<span class=\"token punctuation\">.</span><span class=\"token function\">resolve</span><span class=\"token punctuation\">(</span><span class=\"token string\">\"./src/components/default-page-layout.js\"</span><span class=\"token punctuation\">)</span>\n        <span class=\"token punctuation\">}</span>\n      <span class=\"token punctuation\">}</span>\n    <span class=\"token punctuation\">}</span>\n  <span class=\"token punctuation\">]</span>\n<span class=\"token punctuation\">}</span><span class=\"token punctuation\">;</span></code></pre></div>\n<p>MDX has the concept of a layout that is different than the Gatsby\nconcept of a layout. MDX’s layouts are written using the default\nexport JavaScript syntax in a single MDX file. An MDX layout will wrap\nthe MDX content in an additional component, so this can be a good\nplace for page layout depending on how you are using MDX.</p>\n<div class=\"gatsby-highlight\" data-language=\"javascript\"><pre class=\"language-javascript\"><code class=\"language-javascript\"><span class=\"token keyword\">export</span> <span class=\"token keyword\">default</span> <span class=\"token punctuation\">(</span><span class=\"token punctuation\">{</span> children <span class=\"token punctuation\">}</span><span class=\"token punctuation\">)</span> <span class=\"token operator\">=></span> <span class=\"token punctuation\">(</span>\n  <span class=\"token operator\">&lt;</span>div<span class=\"token operator\">></span>\n    <span class=\"token operator\">&lt;</span>h1<span class=\"token operator\">></span>My Layout<span class=\"token operator\">&lt;</span><span class=\"token operator\">/</span>h1<span class=\"token operator\">></span>\n    <span class=\"token operator\">&lt;</span>div<span class=\"token operator\">></span><span class=\"token punctuation\">{</span>children<span class=\"token punctuation\">}</span><span class=\"token operator\">&lt;</span><span class=\"token operator\">/</span>div<span class=\"token operator\">></span>\n  <span class=\"token operator\">&lt;</span><span class=\"token operator\">/</span>div<span class=\"token operator\">></span>\n<span class=\"token punctuation\">)</span>\n\n# My <span class=\"token constant\">MDX</span>\n\nsome content</code></pre></div>\n<p>or as an import:</p>\n<div class=\"gatsby-highlight\" data-language=\"javascript\"><pre class=\"language-javascript\"><code class=\"language-javascript\"><span class=\"token keyword\">import</span> PageLayout <span class=\"token keyword\">from</span> <span class=\"token string\">'./src/components/page-layout'</span><span class=\"token punctuation\">;</span>\n\n<span class=\"token keyword\">export</span> <span class=\"token keyword\">default</span> PageLayout\n\n# My <span class=\"token constant\">MDX</span>\n\nsome content</code></pre></div>\n<p>Sometimes you don’t want to include the layout in every file, so <code class=\"language-text\">gatsby-mdx</code>\noffers the option to set default layouts in the <code class=\"language-text\">gatsby-config.js</code> plugin\nconfig. Set the key to the <code class=\"language-text\">name</code> set in the <code class=\"language-text\">gatsby-source-filesystem</code> config.\nIf no matching default layout is found, the <code class=\"language-text\">default</code> default layout is used.</p>\n<p>You can also set <code class=\"language-text\">options.defaultLayout.default</code> if you only want to\nuse one layout for all MDX pages that don’t already have a layout defined.</p>\n<div class=\"gatsby-highlight\" data-language=\"js\"><pre class=\"language-js\"><code class=\"language-js\">module<span class=\"token punctuation\">.</span>exports <span class=\"token operator\">=</span> <span class=\"token punctuation\">{</span>\n  siteMetadata<span class=\"token punctuation\">:</span> <span class=\"token punctuation\">{</span>\n    title<span class=\"token punctuation\">:</span> <span class=\"token template-string\"><span class=\"token string\">`Gatsby MDX Kitchen Sink`</span></span>\n  <span class=\"token punctuation\">}</span><span class=\"token punctuation\">,</span>\n  plugins<span class=\"token punctuation\">:</span> <span class=\"token punctuation\">[</span>\n    <span class=\"token punctuation\">{</span>\n      resolve<span class=\"token punctuation\">:</span> <span class=\"token template-string\"><span class=\"token string\">`gatsby-mdx`</span></span><span class=\"token punctuation\">,</span>\n      options<span class=\"token punctuation\">:</span> <span class=\"token punctuation\">{</span>\n        defaultLayouts<span class=\"token punctuation\">:</span> <span class=\"token punctuation\">{</span>\n          posts<span class=\"token punctuation\">:</span> require<span class=\"token punctuation\">.</span><span class=\"token function\">resolve</span><span class=\"token punctuation\">(</span><span class=\"token string\">\"./src/components/posts-layout.js\"</span><span class=\"token punctuation\">)</span><span class=\"token punctuation\">,</span>\n          <span class=\"token keyword\">default</span><span class=\"token punctuation\">:</span> require<span class=\"token punctuation\">.</span><span class=\"token function\">resolve</span><span class=\"token punctuation\">(</span><span class=\"token string\">\"./src/components/default-page-layout.js\"</span><span class=\"token punctuation\">)</span>\n        <span class=\"token punctuation\">}</span>\n      <span class=\"token punctuation\">}</span>\n    <span class=\"token punctuation\">}</span><span class=\"token punctuation\">,</span>\n    <span class=\"token punctuation\">{</span>\n      resolve<span class=\"token punctuation\">:</span> <span class=\"token template-string\"><span class=\"token string\">`gatsby-source-filesystem`</span></span><span class=\"token punctuation\">,</span>\n      options<span class=\"token punctuation\">:</span> <span class=\"token punctuation\">{</span>\n        name<span class=\"token punctuation\">:</span> <span class=\"token template-string\"><span class=\"token string\">`posts`</span></span><span class=\"token punctuation\">,</span>\n        path<span class=\"token punctuation\">:</span> <span class=\"token template-string\"><span class=\"token string\">`</span><span class=\"token interpolation\"><span class=\"token interpolation-punctuation punctuation\">${</span>__dirname<span class=\"token interpolation-punctuation punctuation\">}</span></span><span class=\"token string\">/src/posts/`</span></span>\n      <span class=\"token punctuation\">}</span>\n    <span class=\"token punctuation\">}</span>\n  <span class=\"token punctuation\">]</span>\n<span class=\"token punctuation\">}</span><span class=\"token punctuation\">;</span></code></pre></div>\n<h4 id=\"global-scope\"><a href=\"#global-scope\" aria-label=\"global scope permalink\" class=\"anchor\"><svg aria-hidden=\"true\" focusable=\"false\" height=\"16\" version=\"1.1\" viewBox=\"0 0 16 16\" width=\"16\"><path fill-rule=\"evenodd\" d=\"M4 9h1v1H4c-1.5 0-3-1.69-3-3.5S2.55 3 4 3h4c1.45 0 3 1.69 3 3.5 0 1.41-.91 2.72-2 3.25V8.59c.58-.45 1-1.27 1-2.09C10 5.22 8.98 4 8 4H4c-.98 0-2 1.22-2 2.5S3 9 4 9zm9-3h-1v1h1c1 0 2 1.22 2 2.5S13.98 12 13 12H9c-.98 0-2-1.22-2-2.5 0-.83.42-1.64 1-2.09V6.25c-1.09.53-2 1.84-2 3.25C6 11.31 7.55 13 9 13h4c1.45 0 3-1.69 3-3.5S14.5 6 13 6z\"></path></svg></a>Global scope</h4>\n<p>When importing a react component into your MDX, you can import it using the <code class=\"language-text\">import</code>\nstatement as in JavaScript.</p>\n<div class=\"gatsby-highlight\" data-language=\"mdx\"><pre class=\"language-mdx\"><code class=\"language-mdx\">import { SketchPicker } from &quot;react-color&quot;;\n\n# Hello, world!\n\nHere&#39;s a color picker!\n\n&lt;SketchPicker /&gt;</code></pre></div>\n<p>If you want to allow usage of a component from anywhere, add it to the <code class=\"language-text\">globalScope</code>\nfield in the options inside <code class=\"language-text\">gatsby-config.js</code>:</p>\n<div class=\"gatsby-highlight\" data-language=\"js\"><pre class=\"language-js\"><code class=\"language-js\"><span class=\"token comment\">// gatsby-config.js</span>\nmodule<span class=\"token punctuation\">.</span>exports <span class=\"token operator\">=</span> <span class=\"token punctuation\">{</span>\n  plugins<span class=\"token punctuation\">:</span> <span class=\"token punctuation\">[</span>\n    <span class=\"token punctuation\">{</span>\n      resolve<span class=\"token punctuation\">:</span> <span class=\"token template-string\"><span class=\"token string\">`gatsby-mdx`</span></span><span class=\"token punctuation\">,</span>\n      options<span class=\"token punctuation\">:</span> <span class=\"token punctuation\">{</span>\n        globalScope<span class=\"token punctuation\">:</span> <span class=\"token template-string\"><span class=\"token string\">`\n          import { SketchPicker } from \"react-color\";\n\n          export default { SketchPicker };\n        `</span></span>\n      <span class=\"token punctuation\">}</span>\n    <span class=\"token punctuation\">}</span>\n  <span class=\"token punctuation\">]</span>\n<span class=\"token punctuation\">}</span><span class=\"token punctuation\">;</span></code></pre></div>\n<p>All that is needed is to import the components you wish to be globally available and\nthen put them into an exported object.</p>\n<p>Then, in any MDX file, you can insert the components without the import.</p>\n<div class=\"gatsby-highlight\" data-language=\"mdx\"><pre class=\"language-mdx\"><code class=\"language-mdx\"># Hello, world!\n\nHere&#39;s a color picker\n\n&lt;SketchPicker /&gt;</code></pre></div>\n<blockquote>\n<p>:warning: Note: globalScope is not working yet in any mdx file in <code class=\"language-text\">src/pages</code>, but there is an\nissue to resolve this:</p>\n<p>ChristopherBiscardi/gatsby-mdx#239</p>\n</blockquote>\n<h4 id=\"gatsby-remark-plugins\"><a href=\"#gatsby-remark-plugins\" aria-label=\"gatsby remark plugins permalink\" class=\"anchor\"><svg aria-hidden=\"true\" focusable=\"false\" height=\"16\" version=\"1.1\" viewBox=\"0 0 16 16\" width=\"16\"><path fill-rule=\"evenodd\" d=\"M4 9h1v1H4c-1.5 0-3-1.69-3-3.5S2.55 3 4 3h4c1.45 0 3 1.69 3 3.5 0 1.41-.91 2.72-2 3.25V8.59c.58-.45 1-1.27 1-2.09C10 5.22 8.98 4 8 4H4c-.98 0-2 1.22-2 2.5S3 9 4 9zm9-3h-1v1h1c1 0 2 1.22 2 2.5S13.98 12 13 12H9c-.98 0-2-1.22-2-2.5 0-.83.42-1.64 1-2.09V6.25c-1.09.53-2 1.84-2 3.25C6 11.31 7.55 13 9 13h4c1.45 0 3-1.69 3-3.5S14.5 6 13 6z\"></path></svg></a>Gatsby remark plugins</h4>\n<p>This config option is used for compatibility with a set of plugins many people\n<a href=\"https://www.gatsbyjs.org/plugins/?=gatsby-remark-\">use with remark</a> that require\nthe gatsby environment to function properly. In some cases, like\n<a href=\"https://www.gatsbyjs.org/packages/gatsby-remark-prismjs/?=gatsby-remark-\">gatsby-remark-prismjs</a>,\nit makes more sense to use a library like\n<a href=\"https://github.com/FormidableLabs/prism-react-renderer\">prism-react-renderer</a>\nto render codeblocks using a <a href=\"/api-reference/mdx-provider\">React\ncomponent</a>. In other cases, like\n<a href=\"https://www.gatsbyjs.org/packages/gatsby-remark-images/?=gatsby-remark-\">gatsby-remark-images</a>,\nthe interaction with the Gatsby APIs is well deserved because the\nimages can be optimized by Gatsby and you should continue using it.</p>\n<div class=\"gatsby-highlight\" data-language=\"js\"><pre class=\"language-js\"><code class=\"language-js\"><span class=\"token comment\">// gatsby-config.js</span>\nmodule<span class=\"token punctuation\">.</span>exports <span class=\"token operator\">=</span> <span class=\"token punctuation\">{</span>\n  plugins<span class=\"token punctuation\">:</span> <span class=\"token punctuation\">[</span>\n    <span class=\"token punctuation\">{</span>\n      resolve<span class=\"token punctuation\">:</span> <span class=\"token template-string\"><span class=\"token string\">`gatsby-mdx`</span></span><span class=\"token punctuation\">,</span>\n      options<span class=\"token punctuation\">:</span> <span class=\"token punctuation\">{</span>\n        gatsbyRemarkPlugins<span class=\"token punctuation\">:</span> <span class=\"token punctuation\">[</span>\n          <span class=\"token punctuation\">{</span>\n            resolve<span class=\"token punctuation\">:</span> <span class=\"token template-string\"><span class=\"token string\">`gatsby-remark-images`</span></span><span class=\"token punctuation\">,</span>\n            options<span class=\"token punctuation\">:</span> <span class=\"token punctuation\">{</span>\n              maxWidth<span class=\"token punctuation\">:</span> <span class=\"token number\">590</span>\n            <span class=\"token punctuation\">}</span>\n          <span class=\"token punctuation\">}</span>\n        <span class=\"token punctuation\">]</span>\n      <span class=\"token punctuation\">}</span>\n    <span class=\"token punctuation\">}</span>\n  <span class=\"token punctuation\">]</span>\n<span class=\"token punctuation\">}</span><span class=\"token punctuation\">;</span></code></pre></div>\n<h6 id=\"note\"><a href=\"#note\" aria-label=\"note permalink\" class=\"anchor\"><svg aria-hidden=\"true\" focusable=\"false\" height=\"16\" version=\"1.1\" viewBox=\"0 0 16 16\" width=\"16\"><path fill-rule=\"evenodd\" d=\"M4 9h1v1H4c-1.5 0-3-1.69-3-3.5S2.55 3 4 3h4c1.45 0 3 1.69 3 3.5 0 1.41-.91 2.72-2 3.25V8.59c.58-.45 1-1.27 1-2.09C10 5.22 8.98 4 8 4H4c-.98 0-2 1.22-2 2.5S3 9 4 9zm9-3h-1v1h1c1 0 2 1.22 2 2.5S13.98 12 13 12H9c-.98 0-2-1.22-2-2.5 0-.83.42-1.64 1-2.09V6.25c-1.09.53-2 1.84-2 3.25C6 11.31 7.55 13 9 13h4c1.45 0 3-1.69 3-3.5S14.5 6 13 6z\"></path></svg></a>Note:</h6>\n<p>Using a string reference is currently not supported for <code class=\"language-text\">gatsbyRemarkPlugins</code>. (A PR would be accepted for this)</p>\n<div class=\"gatsby-highlight\" data-language=\"js\"><pre class=\"language-js\"><code class=\"language-js\">gatsbyRemarkPlugins<span class=\"token punctuation\">:</span> <span class=\"token punctuation\">[</span><span class=\"token template-string\"><span class=\"token string\">`gatsby-remark-images`</span></span><span class=\"token punctuation\">]</span><span class=\"token punctuation\">;</span></code></pre></div>\n<h4 id=\"md-plugins\"><a href=\"#md-plugins\" aria-label=\"md plugins permalink\" class=\"anchor\"><svg aria-hidden=\"true\" focusable=\"false\" height=\"16\" version=\"1.1\" viewBox=\"0 0 16 16\" width=\"16\"><path fill-rule=\"evenodd\" d=\"M4 9h1v1H4c-1.5 0-3-1.69-3-3.5S2.55 3 4 3h4c1.45 0 3 1.69 3 3.5 0 1.41-.91 2.72-2 3.25V8.59c.58-.45 1-1.27 1-2.09C10 5.22 8.98 4 8 4H4c-.98 0-2 1.22-2 2.5S3 9 4 9zm9-3h-1v1h1c1 0 2 1.22 2 2.5S13.98 12 13 12H9c-.98 0-2-1.22-2-2.5 0-.83.42-1.64 1-2.09V6.25c-1.09.53-2 1.84-2 3.25C6 11.31 7.55 13 9 13h4c1.45 0 3-1.69 3-3.5S14.5 6 13 6z\"></path></svg></a>MD plugins</h4>\n<p>This is a configuration option that is <a href=\"https://mdxjs.com/plugins\">mirrored from the core MDX\nprocessing pipeline</a>. It enables the use of\n<a href=\"https://github.com/remarkjs/remark/blob/master/doc/plugins.md\">remark\nplugins</a>\nfor processing MDX content.</p>\n<div class=\"gatsby-highlight\" data-language=\"js\"><pre class=\"language-js\"><code class=\"language-js\"><span class=\"token comment\">// gatsby-config.js</span>\nmodule<span class=\"token punctuation\">.</span>exports <span class=\"token operator\">=</span> <span class=\"token punctuation\">{</span>\n  plugins<span class=\"token punctuation\">:</span> <span class=\"token punctuation\">[</span>\n    <span class=\"token punctuation\">{</span>\n      resolve<span class=\"token punctuation\">:</span> <span class=\"token template-string\"><span class=\"token string\">`gatsby-mdx`</span></span><span class=\"token punctuation\">,</span>\n      options<span class=\"token punctuation\">:</span> <span class=\"token punctuation\">{</span>\n        mdPlugins<span class=\"token punctuation\">:</span> <span class=\"token punctuation\">[</span><span class=\"token function\">require</span><span class=\"token punctuation\">(</span><span class=\"token string\">\"remark-abbr\"</span><span class=\"token punctuation\">)</span><span class=\"token punctuation\">]</span>\n      <span class=\"token punctuation\">}</span>\n    <span class=\"token punctuation\">}</span>\n  <span class=\"token punctuation\">]</span>\n<span class=\"token punctuation\">}</span><span class=\"token punctuation\">;</span></code></pre></div>\n<h4 id=\"hast-plugins\"><a href=\"#hast-plugins\" aria-label=\"hast plugins permalink\" class=\"anchor\"><svg aria-hidden=\"true\" focusable=\"false\" height=\"16\" version=\"1.1\" viewBox=\"0 0 16 16\" width=\"16\"><path fill-rule=\"evenodd\" d=\"M4 9h1v1H4c-1.5 0-3-1.69-3-3.5S2.55 3 4 3h4c1.45 0 3 1.69 3 3.5 0 1.41-.91 2.72-2 3.25V8.59c.58-.45 1-1.27 1-2.09C10 5.22 8.98 4 8 4H4c-.98 0-2 1.22-2 2.5S3 9 4 9zm9-3h-1v1h1c1 0 2 1.22 2 2.5S13.98 12 13 12H9c-.98 0-2-1.22-2-2.5 0-.83.42-1.64 1-2.09V6.25c-1.09.53-2 1.84-2 3.25C6 11.31 7.55 13 9 13h4c1.45 0 3-1.69 3-3.5S14.5 6 13 6z\"></path></svg></a>HAST plugins</h4>\n<p>This is a configuration option that is <a href=\"https://mdxjs.com/plugins\">mirrored from the core MDX\nprocessing pipeline</a>. It enables the use of\n<a href=\"https://github.com/rehypejs/rehype/blob/master/doc/plugins.md\">rehype\nplugins</a>\nfor processing MDX content.</p>\n<div class=\"gatsby-highlight\" data-language=\"js\"><pre class=\"language-js\"><code class=\"language-js\"><span class=\"token comment\">// gatsby-config.js</span>\nmodule<span class=\"token punctuation\">.</span>exports <span class=\"token operator\">=</span> <span class=\"token punctuation\">{</span>\n  plugins<span class=\"token punctuation\">:</span> <span class=\"token punctuation\">[</span>\n    <span class=\"token punctuation\">{</span>\n      resolve<span class=\"token punctuation\">:</span> <span class=\"token template-string\"><span class=\"token string\">`gatsby-mdx`</span></span><span class=\"token punctuation\">,</span>\n      options<span class=\"token punctuation\">:</span> <span class=\"token punctuation\">{</span>\n        hastPlugins<span class=\"token punctuation\">:</span> <span class=\"token punctuation\">[</span><span class=\"token function\">require</span><span class=\"token punctuation\">(</span><span class=\"token string\">\"rehype-slug\"</span><span class=\"token punctuation\">)</span><span class=\"token punctuation\">]</span>\n      <span class=\"token punctuation\">}</span>\n    <span class=\"token punctuation\">}</span>\n  <span class=\"token punctuation\">]</span>\n<span class=\"token punctuation\">}</span><span class=\"token punctuation\">;</span></code></pre></div>\n<h4 id=\"media-types\"><a href=\"#media-types\" aria-label=\"media types permalink\" class=\"anchor\"><svg aria-hidden=\"true\" focusable=\"false\" height=\"16\" version=\"1.1\" viewBox=\"0 0 16 16\" width=\"16\"><path fill-rule=\"evenodd\" d=\"M4 9h1v1H4c-1.5 0-3-1.69-3-3.5S2.55 3 4 3h4c1.45 0 3 1.69 3 3.5 0 1.41-.91 2.72-2 3.25V8.59c.58-.45 1-1.27 1-2.09C10 5.22 8.98 4 8 4H4c-.98 0-2 1.22-2 2.5S3 9 4 9zm9-3h-1v1h1c1 0 2 1.22 2 2.5S13.98 12 13 12H9c-.98 0-2-1.22-2-2.5 0-.83.42-1.64 1-2.09V6.25c-1.09.53-2 1.84-2 3.25C6 11.31 7.55 13 9 13h4c1.45 0 3-1.69 3-3.5S14.5 6 13 6z\"></path></svg></a>Media types</h4>\n<p>Deciding what content gets processed by gatsby-mdx. This is an\nadvanced option that is useful for dealing with specialized generated\ncontent. It is not intended to be configured for most users.</p>\n<div class=\"gatsby-highlight\" data-language=\"js\"><pre class=\"language-js\"><code class=\"language-js\"><span class=\"token comment\">// gatsby-config.js</span>\nmodule<span class=\"token punctuation\">.</span>exports <span class=\"token operator\">=</span> <span class=\"token punctuation\">{</span>\n  plugins<span class=\"token punctuation\">:</span> <span class=\"token punctuation\">[</span>\n    <span class=\"token punctuation\">{</span>\n      resolve<span class=\"token punctuation\">:</span> <span class=\"token template-string\"><span class=\"token string\">`gatsby-mdx`</span></span><span class=\"token punctuation\">,</span>\n      options<span class=\"token punctuation\">:</span> <span class=\"token punctuation\">{</span>\n        mediaTypes<span class=\"token punctuation\">:</span> <span class=\"token punctuation\">[</span><span class=\"token template-string\"><span class=\"token string\">`text/markdown`</span></span><span class=\"token punctuation\">,</span> <span class=\"token template-string\"><span class=\"token string\">`text/x-markdown`</span></span><span class=\"token punctuation\">]</span>\n      <span class=\"token punctuation\">}</span>\n    <span class=\"token punctuation\">}</span>\n  <span class=\"token punctuation\">]</span>\n<span class=\"token punctuation\">}</span><span class=\"token punctuation\">;</span></code></pre></div>\n<h5 id=\"explanation\"><a href=\"#explanation\" aria-label=\"explanation permalink\" class=\"anchor\"><svg aria-hidden=\"true\" focusable=\"false\" height=\"16\" version=\"1.1\" viewBox=\"0 0 16 16\" width=\"16\"><path fill-rule=\"evenodd\" d=\"M4 9h1v1H4c-1.5 0-3-1.69-3-3.5S2.55 3 4 3h4c1.45 0 3 1.69 3 3.5 0 1.41-.91 2.72-2 3.25V8.59c.58-.45 1-1.27 1-2.09C10 5.22 8.98 4 8 4H4c-.98 0-2 1.22-2 2.5S3 9 4 9zm9-3h-1v1h1c1 0 2 1.22 2 2.5S13.98 12 13 12H9c-.98 0-2-1.22-2-2.5 0-.83.42-1.64 1-2.09V6.25c-1.09.53-2 1.84-2 3.25C6 11.31 7.55 13 9 13h4c1.45 0 3-1.69 3-3.5S14.5 6 13 6z\"></path></svg></a>Explanation</h5>\n<p>Gatsby includes the media-type of the content on any given node. For\n<code class=\"language-text\">file</code> nodes, we choose whether to process the content with MDX or not\nby the file extension. For remote content or generated content, we\nchoose which nodes to process by looking at the media type.</p>\n<h3 id=\"components\"><a href=\"#components\" aria-label=\"components permalink\" class=\"anchor\"><svg aria-hidden=\"true\" focusable=\"false\" height=\"16\" version=\"1.1\" viewBox=\"0 0 16 16\" width=\"16\"><path fill-rule=\"evenodd\" d=\"M4 9h1v1H4c-1.5 0-3-1.69-3-3.5S2.55 3 4 3h4c1.45 0 3 1.69 3 3.5 0 1.41-.91 2.72-2 3.25V8.59c.58-.45 1-1.27 1-2.09C10 5.22 8.98 4 8 4H4c-.98 0-2 1.22-2 2.5S3 9 4 9zm9-3h-1v1h1c1 0 2 1.22 2 2.5S13.98 12 13 12H9c-.98 0-2-1.22-2-2.5 0-.83.42-1.64 1-2.09V6.25c-1.09.53-2 1.84-2 3.25C6 11.31 7.55 13 9 13h4c1.45 0 3-1.69 3-3.5S14.5 6 13 6z\"></path></svg></a>Components</h3>\n<p>MDX and gatsby-mdx use components for different things like rendering\nand component mappings.</p>\n<h4 id=\"mdxprovider\"><a href=\"#mdxprovider\" aria-label=\"mdxprovider permalink\" class=\"anchor\"><svg aria-hidden=\"true\" focusable=\"false\" height=\"16\" version=\"1.1\" viewBox=\"0 0 16 16\" width=\"16\"><path fill-rule=\"evenodd\" d=\"M4 9h1v1H4c-1.5 0-3-1.69-3-3.5S2.55 3 4 3h4c1.45 0 3 1.69 3 3.5 0 1.41-.91 2.72-2 3.25V8.59c.58-.45 1-1.27 1-2.09C10 5.22 8.98 4 8 4H4c-.98 0-2 1.22-2 2.5S3 9 4 9zm9-3h-1v1h1c1 0 2 1.22 2 2.5S13.98 12 13 12H9c-.98 0-2-1.22-2-2.5 0-.83.42-1.64 1-2.09V6.25c-1.09.53-2 1.84-2 3.25C6 11.31 7.55 13 9 13h4c1.45 0 3-1.69 3-3.5S14.5 6 13 6z\"></path></svg></a>MDXProvider</h4>\n<p><code class=\"language-text\">MDXProvider</code> is a React component that allows you to replace the\nrendering of tags in MDX content. It does this by providing a list of\ncomponents via context to the internal <code class=\"language-text\">MDXTag</code> component that handles\nrendering of base tags like <code class=\"language-text\">p</code> and <code class=\"language-text\">h1</code>. There are two special tags\nthat can be replaced too: <code class=\"language-text\">inlineCode</code> and <code class=\"language-text\">wrapper</code>. <code class=\"language-text\">inlineCode</code> is\nfor inline <code class=\"language-text\">&lt;code&gt;</code> and <code class=\"language-text\">wrapper</code> is the special element that wraps\nall of the MDX content.</p>\n<div class=\"gatsby-highlight\" data-language=\"js\"><pre class=\"language-js\"><code class=\"language-js\"><span class=\"token keyword\">import</span> <span class=\"token punctuation\">{</span> MDXProvider <span class=\"token punctuation\">}</span> <span class=\"token keyword\">from</span> <span class=\"token string\">\"@mdx-js/tag\"</span><span class=\"token punctuation\">;</span>\n\n<span class=\"token keyword\">const</span> <span class=\"token function-variable function\">MyH1</span> <span class=\"token operator\">=</span> props <span class=\"token operator\">=></span> <span class=\"token operator\">&lt;</span>h1 style<span class=\"token operator\">=</span><span class=\"token punctuation\">{</span><span class=\"token punctuation\">{</span> color<span class=\"token punctuation\">:</span> <span class=\"token string\">\"tomato\"</span> <span class=\"token punctuation\">}</span><span class=\"token punctuation\">}</span> <span class=\"token punctuation\">{</span><span class=\"token operator\">...</span>props<span class=\"token punctuation\">}</span> <span class=\"token operator\">/</span><span class=\"token operator\">></span><span class=\"token punctuation\">;</span>\n<span class=\"token keyword\">const</span> <span class=\"token function-variable function\">MyParagraph</span> <span class=\"token operator\">=</span> props <span class=\"token operator\">=></span> <span class=\"token punctuation\">(</span>\n  <span class=\"token operator\">&lt;</span>p style<span class=\"token operator\">=</span><span class=\"token punctuation\">{</span><span class=\"token punctuation\">{</span> fontSize<span class=\"token punctuation\">:</span> <span class=\"token string\">\"18px\"</span><span class=\"token punctuation\">,</span> lineHeight<span class=\"token punctuation\">:</span> <span class=\"token number\">1.6</span> <span class=\"token punctuation\">}</span><span class=\"token punctuation\">}</span> <span class=\"token operator\">/</span><span class=\"token operator\">></span>\n<span class=\"token punctuation\">)</span><span class=\"token punctuation\">;</span>\n\n<span class=\"token keyword\">const</span> components <span class=\"token operator\">=</span> <span class=\"token punctuation\">{</span>\n  h1<span class=\"token punctuation\">:</span> MyH1<span class=\"token punctuation\">,</span>\n  p<span class=\"token punctuation\">:</span> MyParagraph\n<span class=\"token punctuation\">}</span><span class=\"token punctuation\">;</span>\n\n<span class=\"token keyword\">export</span> <span class=\"token keyword\">const</span> <span class=\"token function-variable function\">wrapRootElement</span> <span class=\"token operator\">=</span> <span class=\"token punctuation\">(</span><span class=\"token punctuation\">{</span> element <span class=\"token punctuation\">}</span><span class=\"token punctuation\">)</span> <span class=\"token operator\">=></span> <span class=\"token punctuation\">(</span>\n  <span class=\"token operator\">&lt;</span>MDXProvider components<span class=\"token operator\">=</span><span class=\"token punctuation\">{</span>components<span class=\"token punctuation\">}</span><span class=\"token operator\">></span><span class=\"token punctuation\">{</span>element<span class=\"token punctuation\">}</span><span class=\"token operator\">&lt;</span><span class=\"token operator\">/</span>MDXProvider<span class=\"token operator\">></span>\n<span class=\"token punctuation\">)</span><span class=\"token punctuation\">;</span></code></pre></div>\n<p>The following components can be customized with the MDXProvider:</p>\n<table>\n<thead>\n<tr>\n<th>Tag</th>\n<th>Name</th>\n<th>Syntax</th>\n</tr>\n</thead>\n<tbody>\n<tr>\n<td><code class=\"language-text\">p</code></td>\n<td><a href=\"https://github.com/syntax-tree/mdast#paragraph\">Paragraph</a></td>\n<td></td>\n</tr>\n<tr>\n<td><code class=\"language-text\">h1</code></td>\n<td><a href=\"https://github.com/syntax-tree/mdast#heading\">Heading 1</a></td>\n<td><code class=\"language-text\">#</code></td>\n</tr>\n<tr>\n<td><code class=\"language-text\">h2</code></td>\n<td><a href=\"https://github.com/syntax-tree/mdast#heading\">Heading 2</a></td>\n<td><code class=\"language-text\">##</code></td>\n</tr>\n<tr>\n<td><code class=\"language-text\">h3</code></td>\n<td><a href=\"https://github.com/syntax-tree/mdast#heading\">Heading 3</a></td>\n<td><code class=\"language-text\">###</code></td>\n</tr>\n<tr>\n<td><code class=\"language-text\">h4</code></td>\n<td><a href=\"https://github.com/syntax-tree/mdast#heading\">Heading 4</a></td>\n<td><code class=\"language-text\">####</code></td>\n</tr>\n<tr>\n<td><code class=\"language-text\">h5</code></td>\n<td><a href=\"https://github.com/syntax-tree/mdast#heading\">Heading 5</a></td>\n<td><code class=\"language-text\">#####</code></td>\n</tr>\n<tr>\n<td><code class=\"language-text\">h6</code></td>\n<td><a href=\"https://github.com/syntax-tree/mdast#heading\">Heading 6</a></td>\n<td><code class=\"language-text\">######</code></td>\n</tr>\n<tr>\n<td><code class=\"language-text\">thematicBreak</code></td>\n<td><a href=\"https://github.com/syntax-tree/mdast#thematicbreak\">Thematic break</a></td>\n<td><code class=\"language-text\">***</code></td>\n</tr>\n<tr>\n<td><code class=\"language-text\">blockquote</code></td>\n<td><a href=\"https://github.com/syntax-tree/mdast#blockquote\">Blockquote</a></td>\n<td><code class=\"language-text\">&gt;</code></td>\n</tr>\n<tr>\n<td><code class=\"language-text\">ul</code></td>\n<td><a href=\"https://github.com/syntax-tree/mdast#list\">List</a></td>\n<td><code class=\"language-text\">-</code></td>\n</tr>\n<tr>\n<td><code class=\"language-text\">ol</code></td>\n<td><a href=\"https://github.com/syntax-tree/mdast#list\">Ordered list</a></td>\n<td><code class=\"language-text\">1.</code></td>\n</tr>\n<tr>\n<td><code class=\"language-text\">li</code></td>\n<td><a href=\"https://github.com/syntax-tree/mdast#listitem\">List item</a></td>\n<td></td>\n</tr>\n<tr>\n<td><code class=\"language-text\">table</code></td>\n<td><a href=\"https://github.com/syntax-tree/mdast#table\">Table</a></td>\n<td><code class=\"language-text\">--- | --- | ---</code></td>\n</tr>\n<tr>\n<td><code class=\"language-text\">tr</code></td>\n<td><a href=\"https://github.com/syntax-tree/mdast#tablerow\">Table row</a></td>\n<td><code class=\"language-text\">This | is | a | table row</code></td>\n</tr>\n<tr>\n<td><code class=\"language-text\">td</code>/<code class=\"language-text\">th</code></td>\n<td><a href=\"https://github.com/syntax-tree/mdast#tablecell\">Table cell</a></td>\n<td></td>\n</tr>\n<tr>\n<td><code class=\"language-text\">pre</code></td>\n<td><a href=\"https://github.com/syntax-tree/mdast#code\">Pre</a></td>\n<td></td>\n</tr>\n<tr>\n<td><code class=\"language-text\">code</code></td>\n<td><a href=\"https://github.com/syntax-tree/mdast#code\">Code</a></td>\n<td></td>\n</tr>\n<tr>\n<td><code class=\"language-text\">em</code></td>\n<td><a href=\"https://github.com/syntax-tree/mdast#emphasis\">Emphasis</a></td>\n<td><code class=\"language-text\">_emphasis_</code></td>\n</tr>\n<tr>\n<td><code class=\"language-text\">strong</code></td>\n<td><a href=\"https://github.com/syntax-tree/mdast#strong\">Strong</a></td>\n<td><code class=\"language-text\">**strong**</code></td>\n</tr>\n<tr>\n<td><code class=\"language-text\">delete</code></td>\n<td><a href=\"https://github.com/syntax-tree/mdast#delete\">Delete</a></td>\n<td><code class=\"language-text\">~~strikethrough~~</code></td>\n</tr>\n<tr>\n<td><code class=\"language-text\">code</code></td>\n<td><a href=\"https://github.com/syntax-tree/mdast#inlinecode\">InlineCode</a></td>\n<td></td>\n</tr>\n<tr>\n<td><code class=\"language-text\">hr</code></td>\n<td><a href=\"https://github.com/syntax-tree/mdast#break\">Break</a></td>\n<td><code class=\"language-text\">---</code></td>\n</tr>\n<tr>\n<td><code class=\"language-text\">a</code></td>\n<td><a href=\"https://github.com/syntax-tree/mdast#link\">Link</a></td>\n<td><code class=\"language-text\">&lt;https://mdxjs.com&gt;</code> or <code class=\"language-text\">[MDX](https://mdxjs.com)</code></td>\n</tr>\n<tr>\n<td><code class=\"language-text\">img</code></td>\n<td><a href=\"https://github.com/syntax-tree/mdast#image\">Image</a></td>\n<td><code class=\"language-text\">![alt](https://mdx-logo.now.sh)</code></td>\n</tr>\n</tbody>\n</table>\n<p>It’s important to define the <code class=\"language-text\">components</code> you pass in in a stable way\nso that the references don’t change if you want to be able to navigate\nto a hash. That’s why we defined <code class=\"language-text\">components</code> outside of any render\nfunctions in these examples.</p>\n<h5 id=\"related\"><a href=\"#related\" aria-label=\"related permalink\" class=\"anchor\"><svg aria-hidden=\"true\" focusable=\"false\" height=\"16\" version=\"1.1\" viewBox=\"0 0 16 16\" width=\"16\"><path fill-rule=\"evenodd\" d=\"M4 9h1v1H4c-1.5 0-3-1.69-3-3.5S2.55 3 4 3h4c1.45 0 3 1.69 3 3.5 0 1.41-.91 2.72-2 3.25V8.59c.58-.45 1-1.27 1-2.09C10 5.22 8.98 4 8 4H4c-.98 0-2 1.22-2 2.5S3 9 4 9zm9-3h-1v1h1c1 0 2 1.22 2 2.5S13.98 12 13 12H9c-.98 0-2-1.22-2-2.5 0-.83.42-1.64 1-2.09V6.25c-1.09.53-2 1.84-2 3.25C6 11.31 7.55 13 9 13h4c1.45 0 3-1.69 3-3.5S14.5 6 13 6z\"></path></svg></a>Related</h5>\n<ul>\n<li><a href=\"https://mdxjs.com/getting-started/#mdxprovider\">MDX components</a></li>\n</ul>\n<h4 id=\"mdxrenderer\"><a href=\"#mdxrenderer\" aria-label=\"mdxrenderer permalink\" class=\"anchor\"><svg aria-hidden=\"true\" focusable=\"false\" height=\"16\" version=\"1.1\" viewBox=\"0 0 16 16\" width=\"16\"><path fill-rule=\"evenodd\" d=\"M4 9h1v1H4c-1.5 0-3-1.69-3-3.5S2.55 3 4 3h4c1.45 0 3 1.69 3 3.5 0 1.41-.91 2.72-2 3.25V8.59c.58-.45 1-1.27 1-2.09C10 5.22 8.98 4 8 4H4c-.98 0-2 1.22-2 2.5S3 9 4 9zm9-3h-1v1h1c1 0 2 1.22 2 2.5S13.98 12 13 12H9c-.98 0-2-1.22-2-2.5 0-.83.42-1.64 1-2.09V6.25c-1.09.53-2 1.84-2 3.25C6 11.31 7.55 13 9 13h4c1.45 0 3-1.69 3-3.5S14.5 6 13 6z\"></path></svg></a>MDXRenderer</h4>\n<p><code class=\"language-text\">MDXRenderer</code> is a React component that takes <em>compiled</em> MDX content and\nrenders it. You will need to use this if your MDX content is coming\nfrom a GraphQL page query or <code class=\"language-text\">StaticQuery</code>.</p>\n<p><code class=\"language-text\">MDXRenderer</code> takes any prop and passes it on to your MDX content,\njust like a normal React component.</p>\n<div class=\"gatsby-highlight\" data-language=\"js\"><pre class=\"language-js\"><code class=\"language-js\"><span class=\"token operator\">&lt;</span>MDXRenderer title<span class=\"token operator\">=</span><span class=\"token string\">\"My Stuff!\"</span><span class=\"token operator\">></span><span class=\"token punctuation\">{</span>mdx<span class=\"token punctuation\">.</span>code<span class=\"token punctuation\">.</span>body<span class=\"token punctuation\">}</span><span class=\"token operator\">&lt;</span><span class=\"token operator\">/</span>MDXRenderer<span class=\"token operator\">></span></code></pre></div>\n<p>Using a page query:</p>\n<div class=\"gatsby-highlight\" data-language=\"js\"><pre class=\"language-js\"><code class=\"language-js\"><span class=\"token keyword\">import</span> <span class=\"token punctuation\">{</span> MDXRenderer <span class=\"token punctuation\">}</span> <span class=\"token keyword\">from</span> <span class=\"token string\">\"gatsby-mdx\"</span><span class=\"token punctuation\">;</span>\n\n<span class=\"token keyword\">export</span> <span class=\"token keyword\">default</span> <span class=\"token keyword\">class</span> <span class=\"token class-name\">MyPageLayout</span> <span class=\"token punctuation\">{</span>\n  <span class=\"token function\">render</span><span class=\"token punctuation\">(</span><span class=\"token punctuation\">)</span> <span class=\"token punctuation\">{</span>\n    <span class=\"token operator\">&lt;</span>MDXRenderer<span class=\"token operator\">></span><span class=\"token punctuation\">{</span><span class=\"token keyword\">this</span><span class=\"token punctuation\">.</span>props<span class=\"token punctuation\">.</span>data<span class=\"token punctuation\">.</span>mdx<span class=\"token punctuation\">.</span>code<span class=\"token punctuation\">.</span>body<span class=\"token punctuation\">}</span><span class=\"token operator\">&lt;</span><span class=\"token operator\">/</span>MDXRenderer<span class=\"token operator\">></span><span class=\"token punctuation\">;</span>\n  <span class=\"token punctuation\">}</span>\n<span class=\"token punctuation\">}</span>\n\n<span class=\"token keyword\">export</span> <span class=\"token keyword\">const</span> pageQuery <span class=\"token operator\">=</span> graphql<span class=\"token template-string\"><span class=\"token string\">`\n  query MDXQuery($id: String!) {\n    mdx(id: { eq: $id }) {\n      id\n      code {\n        body\n      }\n    }\n  }\n`</span></span><span class=\"token punctuation\">;</span></code></pre></div>\n<h2 id=\"license\"><a href=\"#license\" aria-label=\"license permalink\" class=\"anchor\"><svg aria-hidden=\"true\" focusable=\"false\" height=\"16\" version=\"1.1\" viewBox=\"0 0 16 16\" width=\"16\"><path fill-rule=\"evenodd\" d=\"M4 9h1v1H4c-1.5 0-3-1.69-3-3.5S2.55 3 4 3h4c1.45 0 3 1.69 3 3.5 0 1.41-.91 2.72-2 3.25V8.59c.58-.45 1-1.27 1-2.09C10 5.22 8.98 4 8 4H4c-.98 0-2 1.22-2 2.5S3 9 4 9zm9-3h-1v1h1c1 0 2 1.22 2 2.5S13.98 12 13 12H9c-.98 0-2-1.22-2-2.5 0-.83.42-1.64 1-2.09V6.25c-1.09.53-2 1.84-2 3.25C6 11.31 7.55 13 9 13h4c1.45 0 3-1.69 3-3.5S14.5 6 13 6z\"></path></svg></a>License</h2>\n<p>MIT</p>","timeToRead":11}}}},"pageContext":{"slug":"/packages/gatsby-mdx/","id":"1cb39a06-2938-5337-869c-295339f457a1","layout":"plugins"}}