{"data":{"markdownRemark":null,"npmPackage":{"name":"gatsby-source-git-commit","description":"A gatsby source plugin to include the git commit hash within a GraphQL node.","keywords":["gatsby","gatsby-plugin","gatsby-source-plugin"],"lastPublisher":{"name":"jamesdanylik","avatar":"https://gravatar.com/avatar/9b3c60cd4c68ed005185c60b6d80479e"},"repository":{"url":"https://github.com/jamesdanylik/gatsby-source-git-commit"},"readme":{"childMarkdownRemark":{"html":"<p>ERROR: No README data found!</p>","timeToRead":1}}}},"pageContext":{"slug":"/packages/gatsby-source-git-commit/","id":"43bf6115-4441-5dff-8c82-1a0bfb1da696","layout":"plugins"}}